omnizart/__init__.py
omnizart/base.py
omnizart/beat/__init__.py
omnizart/beat/app.py
omnizart/beat/features.py
omnizart/beat/inference.py
omnizart/beat/prediction.py
omnizart/callbacks.py
omnizart/checkpoints/beat/beat_blstm/configurations.yaml
omnizart/checkpoints/beat/beat_blstm/saved_model.pb
omnizart/checkpoints/beat/beat_blstm/variables/variables.index
omnizart/checkpoints/chord/chord_v1/configurations.yaml
omnizart/checkpoints/chord/chord_v1/saved_model.pb
omnizart/checkpoints/chord/chord_v1/variables/variables.index
omnizart/checkpoints/drum/drum_keras/configurations.yaml
omnizart/checkpoints/drum/drum_keras/saved_model.pb
omnizart/checkpoints/drum/drum_keras/variables/variables.index
omnizart/checkpoints/music/music_note_stream/configurations.yaml
omnizart/checkpoints/music/music_note_stream/saved_model.pb
omnizart/checkpoints/music/music_note_stream/variables/variables.index
omnizart/checkpoints/music/music_piano/configurations.yaml
omnizart/checkpoints/music/music_piano/saved_model.pb
omnizart/checkpoints/music/music_piano/variables/variables.index
omnizart/checkpoints/music/music_piano-v2/configurations.yaml
omnizart/checkpoints/music/music_piano-v2/saved_model.pb
omnizart/checkpoints/music/music_piano-v2/variables/variables.index
omnizart/checkpoints/music/music_pop/configurations.yaml
omnizart/checkpoints/music/music_pop/saved_model.pb
omnizart/checkpoints/music/music_pop/variables/variables.index
omnizart/checkpoints/patch_cnn/patch_cnn_melody/configurations.yaml
omnizart/checkpoints/patch_cnn/patch_cnn_melody/saved_model.pb
omnizart/checkpoints/patch_cnn/patch_cnn_melody/variables/variables.index
omnizart/checkpoints/vocal/vocal_contour/configurations.yaml
omnizart/checkpoints/vocal/vocal_contour/saved_model.pb
omnizart/checkpoints/vocal/vocal_contour/variables/variables.index
omnizart/checkpoints/vocal/vocal_semi/configurations.yaml
omnizart/checkpoints/vocal/vocal_semi/saved_model.pb
omnizart/checkpoints/vocal/vocal_semi/variables/variables.index
omnizart-0.5.0.dist-info/entry_points.txt
omnizart-0.5.0.dist-info/LICENSE
omnizart-0.5.0.dist-info/WHEEL
omnizart-0.5.0.dist-info/METADATA
omnizart-0.5.0.dist-info/RECORD
