Metadata-Version: 2.1
Name: omnizart
Version: 0.5.0
Summary: Omniscient Mozart, being able to transcribe everything in the music.
Home-page: https://sites.google.com/view/mctl/home
License: MIT
Keywords: automatic music transcription,drum transcription,vocal transcription,beat tracking
Author: BreezeWhite
Author-email: miyashita2010@tuta.io
Requires-Python: >=3.6.1,<3.9
Classifier: Intended Audience :: Developers
Classifier: Intended Audience :: Science/Research
Classifier: License :: OSI Approved :: MIT License
Classifier: Programming Language :: Python :: 3
Classifier: Programming Language :: Python :: 3 :: Only
Classifier: Programming Language :: Python :: 3.7
Classifier: Programming Language :: Python :: 3.8
Classifier: Topic :: Documentation :: Sphinx
Classifier: Topic :: Multimedia :: Sound/Audio :: MIDI
Classifier: Topic :: Software Development :: Libraries :: Python Modules
Classifier: Topic :: Software Development :: Version Control :: Git
Requires-Dist: click (>=7.1.2,<8.0.0)
Requires-Dist: jsonschema (>=3.2.0,<4.0.0)
Requires-Dist: librosa (>=0.8.0,<0.9.0)
Requires-Dist: madmom (>=0.16.1,<0.17.0)
Requires-Dist: mir_eval (>=0.6,<0.7)
Requires-Dist: pillow (>=8.3.2,<9.0.0)
Requires-Dist: pretty_midi (>=0.2.9,<0.3.0)
Requires-Dist: pyfluidsynth (>=1.2.5,<2.0.0)
Requires-Dist: pyyaml (>=5.3.1,<6.0.0)
Requires-Dist: spleeter (>=2.3.0,<3.0.0)
Requires-Dist: tensorflow (==2.5.0)
Requires-Dist: tqdm (>=4.49.0,<5.0.0)
Requires-Dist: urllib3 (==1.26.4)
Requires-Dist: vamp (>=1.1.0,<2.0.0)
Project-URL: Documentation, https://music-and-culture-technology-lab.github.io/omnizart-doc/
Project-URL: Repository, https://github.com/Music-and-Culture-Technology-Lab/omnizart
